floword/__init__.py
floword/alembic.ini
floword/app.py
floword/cli.py
floword/config.py
floword/dbutils.py
floword/log.py
floword/orm.py
floword/users.py
floword/alembic/README
floword/alembic/env.py
floword/alembic/script.py.mako
floword/alembic/versions/.gitkeep
floword/llms/__init__.py
floword/llms/mcp_agent.py
floword/llms/models.py
floword/mcp/__init__.py
floword/mcp/clinet.py
floword/mcp/manager.py
floword/mcp/mcp.json
floword/prompts/system-conversation.md
floword/prompts/system-workflow.md
floword/router/__init__.py
floword/router/api/__init__.py
floword/router/api/config.py
floword/router/api/params.py
floword/router/api/v1/__init__.py
floword/router/api/v1/conversation.py
floword/router/api/v1/workflow.py
floword/router/controller/__init__.py
floword/router/controller/conversation.py
floword/router/controller/workflow.py
floword/router/streamer/__init__.py
floword/router/streamer/memory.py
floword/router/streamer/redis.py
floword/ui/__init__.py
floword/ui/api_client.py
floword/ui/app.py
floword/ui/backend_manager.py
floword/ui/message_processor.py
floword/ui/components/__init__.py
floword/ui/components/backend_config_page.py
floword/ui/components/chat_interface.py
floword/ui/components/conversation_list.py
floword/ui/components/conversation_page.py
floword/ui/components/tool_call_popup.py
floword/ui/models/__init__.py
floword/ui/models/backend_config.py
floword/ui/models/conversation.py
floword-0.0.4.dist-info/METADATA
floword-0.0.4.dist-info/WHEEL
floword-0.0.4.dist-info/entry_points.txt
floword-0.0.4.dist-info/licenses/LICENSE
floword-0.0.4.dist-info/RECORD
