Metadata-Version: 2.4
Name: floword
Version: 0.0.4
Summary: Build workflow with natural language
Project-URL: Homepage, https://ai-zerolab.github.io/floword/
Project-URL: Repository, https://github.com/ai-zerolab/floword
Project-URL: Documentation, https://ai-zerolab.github.io/floword/
Author-email: Wh1isper <jizhongsheng957@gmail.com>
License-File: LICENSE
Keywords: python
Classifier: Intended Audience :: Developers
Classifier: Programming Language :: Python
Classifier: Programming Language :: Python :: 3
Classifier: Programming Language :: Python :: 3.10
Classifier: Programming Language :: Python :: 3.11
Classifier: Programming Language :: Python :: 3.12
Classifier: Programming Language :: Python :: 3.13
Classifier: Topic :: Software Development :: Libraries :: Python Modules
Requires-Python: <4.0,>=3.10
Requires-Dist: aiosqlite>=0.21.0
Requires-Dist: alembic>=1.14.1
Requires-Dist: click>=8.1.8
Requires-Dist: fastapi[standard]>=0.115.10
Requires-Dist: gradio>=5.20.1
Requires-Dist: httpx-sse>=0.4.0
Requires-Dist: httpx>=0.28.1
Requires-Dist: loguru>=0.7.3
Requires-Dist: mcp[cli]>=1.3.0
Requires-Dist: psycopg[binary,pool]>=3.2.5
Requires-Dist: pydantic-ai>=0.0.39
Requires-Dist: pydantic-settings[toml]>=2.8.0
Requires-Dist: pydantic>=2.10.6
Requires-Dist: python-jose[cryptography]>=3.4.0
Requires-Dist: redis>=5.2.1
Requires-Dist: sqlalchemy[asyncio]>=2.0.38
Requires-Dist: sse-starlette>=2.2.1
Requires-Dist: starlette>=0.46.0
Requires-Dist: uvicorn[standard]>=0.34.0
